{
    "cmd": "/private/home/pfz/miniconda3/envs/img/bin/python train.py",
    "git": "git@github.com:fairinternal/videoseal.git",
    "preload": "MKL_THREADING_LAYER=GNU",
    "commit": "compression-augmentation",
    "precmd": [],
    "params": {
        "image_dataset":        "coco",
        "video_dataset":        "sa-v",
        "augmentation_config":  "configs/simple_augs.yaml",
        "embedder_model":       "vae_small_bw",
        "extractor_model":      "sam_tiny",
        "video_start":          10,
        "img_size":             256,
        "img_size_extractor":   256,
        "iter_per_epoch":       1000,
        "iter_per_valid":       20,
        "batch_size":           32,
        "batch_size_eval":      32,
        "num_clips":            1,
        "frame_step":           1,
        "frames_per_clip":      64,
        "videowam_step_size":   [2, 4, 8],
        "epochs":               100,
        "optimizer":            "AdamW,lr=1e-4",
        "scheduler":            "CosineLRScheduler,lr_min=1e-6,t_initial=100,warmup_lr_init=1e-6,warmup_t=5",
        "seed":                 666,
        "perceptual_loss":      "mse",
        "lambda_i":             0.0,
        "lambda_d":             0.0,
        "lambda_det":           0.0,
        "lambda_dec":           1.0,
        "nbits":                32,
        "scaling_i":            1.0,
        "scaling_w":            0.05,
        "balanced":             true,
        "workers":              0,
        "master_port":          "__SAMPLE__(10000, 20000)"
    },
    "machine": {
        "constraint": "volta32gb",
        "gres": "gpu:8",
        "nodes": "1",
        "tasks-per-node": "8",
        "partition": "learnlab",
        "cpus-per-task": "10",
        "time": 4320,
        "mem-per-cpu": "10G"
    },
    "meta": {
        "group": "",
        "name": "1008_vseal_codec_wmfps",
        "dest-arg": "yes",
        "dest-name": "output_dir"
    }
}